demo/__init__.py
demo/run.py
demo/pages/__init__.py
demo/pages/adr_page.py
demo/pages/image_page.py
demo/tests/__init__.py
demo/tests/adr_script.py
demo/tests/test_adr.py
testadr/__init__.py
testadr/case.py
testadr/cli.py
testadr/page.py
testadr/scaffold.py
testadr/core/__init__.py
testadr/core/android/__init__.py
testadr/core/android/common.py
testadr/core/android/driver.py
testadr/core/android/element.py
testadr/core/api/__init__.py
testadr/core/api/request.py
testadr/core/image/__init__.py
testadr/core/image/driver.py
testadr/core/image/element.py
testadr/core/ocr/__init__.py
testadr/core/ocr/driver.py
testadr/core/ocr/element.py
testadr/running/__init__.py
testadr/running/conf.yml
testadr/running/runner.py
testadr/testdata/__init__.py
testadr/testdata/data.py
testadr/utils/__init__.py
testadr/utils/allure_util.py
testadr/utils/common.py
testadr/utils/config.py
testadr/utils/des_util.py
testadr/utils/dingtalk.py
testadr/utils/excel.py
testadr/utils/exceptions.py
testadr/utils/log.py
testadr/utils/mail.py
testadr/utils/mysql_util.py
testadr/utils/pytest_util.py
testadr/utils/swagger_util.py
testadr-0.0.9.dist-info/METADATA
testadr-0.0.9.dist-info/WHEEL
testadr-0.0.9.dist-info/entry_points.txt
testadr-0.0.9.dist-info/top_level.txt
testadr-0.0.9.dist-info/RECORD
